zeroshot_classifier
